Metadata-Version: 2.1
Name: oneNeuron-pypi-amit04
Version: 0.0.3
Summary: its a implementation of perceptron
Home-page: https://github.com/amit04/oneNeuron_pypi
Author: amit04
Author-email: amit.chawarekar@gmail.com
License: UNKNOWN
Project-URL: Bug Tracker, https://github.com/pypa/sampleproject/issues
Platform: UNKNOWN
Classifier: Programming Language :: Python :: 3
Classifier: License :: OSI Approved :: MIT License
Classifier: Operating System :: OS Independent
Requires-Python: >=3.7
License-File: LICENSE
